howmanyweeks/__init__.py
howmanyweeks-0.2.1.dist-info/METADATA
howmanyweeks-0.2.1.dist-info/WHEEL
howmanyweeks-0.2.1.dist-info/entry_points.txt
howmanyweeks-0.2.1.dist-info/RECORD
