Metadata-Version: 2.4
Name: howmanyweeks
Version: 0.2.1
Summary: Add your description here
Requires-Python: >=3.8
